README.md
setup.py
logrpy/__init__.py
logrpy/aes.py
logrpy/count.py
logrpy/counter.py
logrpy/levels.py
logrpy/logger.py
logrpy/logr.py
logrpy/utils.py
logrpy.egg-info/PKG-INFO
logrpy.egg-info/SOURCES.txt
logrpy.egg-info/dependency_links.txt
logrpy.egg-info/requires.txt
logrpy.egg-info/top_level.txt