Metadata-Version: 1.0
Name: logrpy
Version: 1.0.14
Summary: Logr client library for Python.
Home-page: https://github.com/504dev/logr-python-client
Author: Kozhurkin Dima
Author-email: kozhurkin.dima@gmail.com
License: UNKNOWN
Platform: UNKNOWN
